noisecc/__init__.py
noisecc/chunk/__init__.py
noisecc/chunk/chunkclass.py
noisecc/chunk/chunkdata.py
noisecc/chunk/wrapper.py
noisecc/corr/__init__.py
noisecc/corr/corrclass.py
noisecc/corr/corrdata.py
noisecc/corr/wrapper.py
noisecc/io/__init__.py
noisecc/io/load.py
noisecc/rfft/__init__.py
noisecc/rfft/rfftclass.py
noisecc/rfft/rfftdata.py
noisecc/rfft/wrapper.py
noisecc/stack/__init__.py
noisecc/stack/backup/lib.py
noisecc/stack/stackclass.py
noisecc/stack/stackdata.py
noisecc/stack/utils.py
noisecc/stack/wrapper.py
noisecc/tests/__init__.py
noisecc/tests/test_chunk/__init__.py
noisecc/tests/test_chunk/test_chunk.py
noisecc/tests/test_chunk/test_wrapper.py
noisecc/tests/test_corr/__init__.py
noisecc/tests/test_corr/test_corr.py
noisecc/tests/test_corr/test_wrapper.py
noisecc/tests/test_io/__init__.py
noisecc/tests/test_io/test_load.py
noisecc/tests/test_rfft/__init__.py
noisecc/tests/test_rfft/test_rfft.py
noisecc/tests/test_rfft/test_wrapper.py
noisecc/tests/test_stack/__init__.py
noisecc/tests/test_stack/test_stack.py
noisecc/tests/test_stack/test_wrapper.py
noisecc/tests/test_utils/__init__.py
noisecc/tests/test_utils/test_split.py
noisecc/tests/test_utils/test_timestamp.py
noisecc/tests/test_utils/test_whiten.py
noisecc/utils/__init__.py
noisecc/utils/split.py
noisecc/utils/timestamp.py
noisecc/utils/viz_tools.py
noisecc/utils/whiten.py
noisecc-0.0.2.dist-info/LICENSE
noisecc-0.0.2.dist-info/METADATA
noisecc-0.0.2.dist-info/WHEEL
noisecc-0.0.2.dist-info/RECORD
